eyepy/__init__.py
eyepy/config.py
eyepy/core/__init__.py
eyepy/core/annotations.py
eyepy/core/eyebscan.py
eyepy/core/eyeenface.py
eyepy/core/eyemeta.py
eyepy/core/eyevolume.py
eyepy/core/filter.py
eyepy/core/grids.py
eyepy/core/mask_compression.py
eyepy/core/plotting.py
eyepy/core/utils.py
eyepy/data/__init__.py
eyepy/io/__init__.py
eyepy/io/import_functions.py
eyepy/io/utils.py
eyepy/io/he/__init__.py
eyepy/io/he/e2e_format.py
eyepy/io/he/e2e_reader.py
eyepy/io/he/vol_reader.py
eyepy/io/he/xml_reader.py
eyepy/quant/__init__.py
eyepy/quant/metrics.py
eyepy/quant/regions.py
eyepy/quant/spatial.py
eyepy-0.19.0.dist-info/METADATA
eyepy-0.19.0.dist-info/WHEEL
eyepy-0.19.0.dist-info/licenses/LICENSE
eyepy-0.19.0.dist-info/RECORD
