Metadata-Version: 2.4
Name: eyepy
Version: 0.19.0
Summary: A python package to read, analyse and visualize OCT and fundus data form various sources.
Project-URL: Repository, https://github.com/MedVisBonn/eyepy
Author-email: Olivier Morelle <oli4morelle@gmail.com>
License-Expression: MIT
License-File: LICENSE
Keywords: oct,ophthalmology,spectralis,visualization
Classifier: Development Status :: 4 - Beta
Classifier: Intended Audience :: Developers
Classifier: Intended Audience :: Healthcare Industry
Classifier: Intended Audience :: Science/Research
Classifier: License :: OSI Approved :: MIT License
Classifier: Natural Language :: English
Classifier: Operating System :: OS Independent
Classifier: Programming Language :: Python :: 3 :: Only
Classifier: Programming Language :: Python :: 3.9
Classifier: Programming Language :: Python :: 3.10
Classifier: Programming Language :: Python :: 3.11
Classifier: Programming Language :: Python :: 3.12
Classifier: Programming Language :: Python :: 3.13
Classifier: Topic :: Scientific/Engineering :: Image Processing
Classifier: Topic :: Scientific/Engineering :: Medical Science Apps.
Classifier: Topic :: Scientific/Engineering :: Visualization
Classifier: Topic :: Software Development :: Libraries :: Python Modules
Requires-Python: <4.0,>=3.9
Requires-Dist: construct>=2.10.68
Requires-Dist: imageio<3,>=2.25.1
Requires-Dist: matplotlib>=3.9.4
Requires-Dist: numpy>=1.22.0
Requires-Dist: scikit-image>=0.22.0
Provides-Extra: all
Requires-Dist: construct-typing>=0.7.0; extra == 'all'
Requires-Dist: itk<6,>=5.3.0; extra == 'all'
Requires-Dist: oct-converter<0.7,>=0.6.1; extra == 'all'
Requires-Dist: pandas>1.5.3; extra == 'all'
Provides-Extra: build
Requires-Dist: uv~=0.9.5; extra == 'build'
Provides-Extra: e2e
Requires-Dist: construct-typing>=0.7.0; extra == 'e2e'
Provides-Extra: fda
Requires-Dist: oct-converter<0.7,>=0.6.1; extra == 'fda'
Provides-Extra: itk
Requires-Dist: itk<6,>=5.3.0; extra == 'itk'
Provides-Extra: pandas
Requires-Dist: pandas>1.5.3; extra == 'pandas'
